autofuzzts/__init__.py
autofuzzts/config.py
autofuzzts/pipeline.py
autofuzzts/utils.py
autofuzzts/data/__init__.py
autofuzzts/data/data_loader.py
autofuzzts/data_validation/__init__.py
autofuzzts/data_validation/validate.py
autofuzzts/evaluation/__init__.py
autofuzzts/models/__init__.py
autofuzzts/models/fuzzy_classifier.py
autofuzzts/models/mlp_nas.py
autofuzzts/partition/__init__.py
autofuzzts/partition/fuzzy_clust_fun.py
autofuzzts/partition/fuzzy_clust_fun_orig.py
autofuzzts/partition/partition.py
autofuzzts/partition/visualize_partition.py
autofuzzts/preprocess/__init__.py
autofuzzts/preprocess/prep_for_model.py
autofuzzts/preprocess/preprocess.py
autofuzzts-0.1.2.dist-info/licenses/LICENSE
autofuzzts-0.1.2.dist-info/METADATA
autofuzzts-0.1.2.dist-info/WHEEL
autofuzzts-0.1.2.dist-info/top_level.txt
autofuzzts-0.1.2.dist-info/RECORD
